azure/storage/queue/__init__.py
azure/storage/queue/_deserialize.py
azure/storage/queue/_encryption.py
azure/storage/queue/_message_encoding.py
azure/storage/queue/_models.py
azure/storage/queue/_queue_client.py
azure/storage/queue/_queue_client_helpers.py
azure/storage/queue/_queue_service_client.py
azure/storage/queue/_queue_service_client_helpers.py
azure/storage/queue/_serialize.py
azure/storage/queue/_shared_access_signature.py
azure/storage/queue/_version.py
azure/storage/queue/py.typed
azure/storage/queue/_generated/__init__.py
azure/storage/queue/_generated/_azure_queue_storage.py
azure/storage/queue/_generated/_configuration.py
azure/storage/queue/_generated/_patch.py
azure/storage/queue/_generated/py.typed
azure/storage/queue/_generated/_utils/__init__.py
azure/storage/queue/_generated/_utils/serialization.py
azure/storage/queue/_generated/aio/__init__.py
azure/storage/queue/_generated/aio/_azure_queue_storage.py
azure/storage/queue/_generated/aio/_configuration.py
azure/storage/queue/_generated/aio/_patch.py
azure/storage/queue/_generated/aio/operations/__init__.py
azure/storage/queue/_generated/aio/operations/_message_id_operations.py
azure/storage/queue/_generated/aio/operations/_messages_operations.py
azure/storage/queue/_generated/aio/operations/_patch.py
azure/storage/queue/_generated/aio/operations/_queue_operations.py
azure/storage/queue/_generated/aio/operations/_service_operations.py
azure/storage/queue/_generated/models/__init__.py
azure/storage/queue/_generated/models/_azure_queue_storage_enums.py
azure/storage/queue/_generated/models/_models_py3.py
azure/storage/queue/_generated/models/_patch.py
azure/storage/queue/_generated/operations/__init__.py
azure/storage/queue/_generated/operations/_message_id_operations.py
azure/storage/queue/_generated/operations/_messages_operations.py
azure/storage/queue/_generated/operations/_patch.py
azure/storage/queue/_generated/operations/_queue_operations.py
azure_storage_queue-12.14.0.dist-info/licenses/LICENSE
azure_storage_queue-12.14.0.dist-info/METADATA
azure_storage_queue-12.14.0.dist-info/WHEEL
azure_storage_queue-12.14.0.dist-info/top_level.txt
azure_storage_queue-12.14.0.dist-info/RECORD
