Metadata-Version: 2.4
Name: azure-storage-queue
Version: 12.14.0
Summary: Microsoft Azure Azure Queue Storage Client Library for Python
Home-page: https://github.com/Azure/azure-sdk-for-python/tree/main/sdk/storage/azure-storage-queue
Author: Microsoft Corporation
Author-email: ascl@microsoft.com
License: MIT License
Keywords: azure,azure sdk
Classifier: Development Status :: 5 - Production/Stable
Classifier: Programming Language :: Python
Classifier: Programming Language :: Python :: 3 :: Only
Classifier: Programming Language :: Python :: 3
Classifier: Programming Language :: Python :: 3.9
Classifier: Programming Language :: Python :: 3.10
Classifier: Programming Language :: Python :: 3.11
Classifier: Programming Language :: Python :: 3.12
Classifier: License :: OSI Approved :: MIT License
Requires-Python: >=3.9
License-File: LICENSE
Requires-Dist: azure-core>=1.30.0
Requires-Dist: cryptography>=2.1.4
Requires-Dist: typing-extensions>=4.6.0
Requires-Dist: isodate>=0.6.1
Provides-Extra: aio
Requires-Dist: azure-core[aio]>=1.30.0; extra == "aio"
Dynamic: author
Dynamic: author-email
Dynamic: classifier
Dynamic: description
Dynamic: description-content-type
Dynamic: home-page
Dynamic: keywords
Dynamic: license
Dynamic: license-file
Dynamic: provides-extra
Dynamic: requires-dist
Dynamic: requires-python
Dynamic: summary
